dependency_miner/__init__.py
dependency_miner/ltminer.py
dependency_miner/settings.py
dependency_miner_pm4py-1.0.1.dist-info/LICENSE
dependency_miner_pm4py-1.0.1.dist-info/METADATA
dependency_miner_pm4py-1.0.1.dist-info/WHEEL
dependency_miner_pm4py-1.0.1.dist-info/top_level.txt
dependency_miner_pm4py-1.0.1.dist-info/RECORD
