Metadata-Version: 2.1
Name: dependency-miner-pm4py
Version: 1.0.1
Summary: It mines long-term dependencies between events and results into a Precise model
Home-page: https://github.com/AshwiniJogbhat/dependency-miner-pm4py
Author: Ashwini Jogbhat
Author-email: ashwini.jogbhat@rwth-aachen.de
License: MIT
Platform: UNKNOWN
Classifier: License :: OSI Approved :: MIT License
Classifier: Programming Language :: Python :: 3.8
Classifier: Programming Language :: Python :: 3.9
Requires-Dist: numpy
Requires-Dist: pm4py
